splashpy/__init__.py
splashpy/client.py
splashpy/server.py
splashpy/assets/__init__.py
splashpy/assets/img/__init__.py
splashpy/componants/__init__.py
splashpy/componants/blockfactory.py
splashpy/componants/config.py
splashpy/componants/encoder.py
splashpy/componants/fieldfactory.py
splashpy/componants/files.py
splashpy/componants/logger.py
splashpy/componants/validator.py
splashpy/componants/werkzeug.py
splashpy/const/__init__.py
splashpy/core/__init__.py
splashpy/core/framework.py
splashpy/faker/__init__.py
splashpy/faker/client.py
splashpy/faker/model.py
splashpy/faker/primary.py
splashpy/faker/short.py
splashpy/helpers/__init__.py
splashpy/helpers/fields.py
splashpy/helpers/files.py
splashpy/helpers/list.py
splashpy/helpers/logger.py
splashpy/helpers/objects.py
splashpy/helpers/price.py
splashpy/models/__init__.py
splashpy/models/client.py
splashpy/models/configurator.py
splashpy/models/object.py
splashpy/models/server.py
splashpy/models/widget.py
splashpy/models/objects/__init__.py
splashpy/models/objects/intel.py
splashpy/models/objects/interfaces.py
splashpy/models/objects/parser.py
splashpy/models/widgets/__init__.py
splashpy/models/widgets/interfaces.py
splashpy/routers/__init__.py
splashpy/routers/admin.py
splashpy/routers/base.py
splashpy/routers/files.py
splashpy/routers/objects.py
splashpy/routers/widgets.py
splashpy/soap/__init__.py
splashpy/soap/c14n.py
splashpy/soap/client.py
splashpy/soap/helpers.py
splashpy/soap/server.py
splashpy/soap/simplexml.py
splashpy/soap/transport.py
splashpy/soap/wsse.py
splashpy/soap/xmlsec.py
splashpy/templates/__init__.py
splashpy/templates/widgets.py
splashpy/test/__init__.py
splashpy/test/test_encoder.py
splashpy-0.4.3.data/data/python.ico
splashpy-0.4.3.data/data/python.png
splashpy-0.4.3.dist-info/licenses/LICENSE
splashpy-0.4.3.dist-info/METADATA
splashpy-0.4.3.dist-info/WHEEL
splashpy-0.4.3.dist-info/top_level.txt
splashpy-0.4.3.dist-info/RECORD
