Metadata-Version: 2.4
Name: splashpy
Version: 0.4.3
Summary: Foundation Package for Splash Py Clients
Home-page: https://github.com/SplashSync/PyCore
Author: SplashSync
Author-email: contact@splashsync.com
License: MIT
Classifier: Programming Language :: Python
Classifier: Development Status :: 1 - Planning
Classifier: License :: OSI Approved :: MIT License
Classifier: Natural Language :: French
Classifier: Operating System :: OS Independent
Classifier: Programming Language :: Python :: 3.6
Classifier: Topic :: Communications
License-File: LICENSE
Requires-Dist: pycryptodome
Requires-Dist: crypto
Dynamic: author
Dynamic: author-email
Dynamic: classifier
Dynamic: home-page
Dynamic: license
Dynamic: license-file
Dynamic: requires-dist
Dynamic: summary
